simplepup/__init__.py
simplepup/puppetdb.py
simplepup/cli/__init__.py
simplepup/cli/query.py
simplepup-0.0.4.dist-info/DESCRIPTION.rst
simplepup-0.0.4.dist-info/METADATA
simplepup-0.0.4.dist-info/RECORD
simplepup-0.0.4.dist-info/WHEEL
simplepup-0.0.4.dist-info/entry_points.txt
simplepup-0.0.4.dist-info/metadata.json
simplepup-0.0.4.dist-info/top_level.txt
