Metadata-Version: 2.0
Name: simplepup
Version: 0.0.4
Summary: PuppetDB access library and query tool
Home-page: http://github.com/danielparks/simplepup
Author: Daniel Parks
Author-email: os-simplepup@demonhorse.org
License: BSD
Platform: UNKNOWN
Classifier: Development Status :: 3 - Alpha
Classifier: Intended Audience :: Developers
Classifier: Intended Audience :: System Administrators
Classifier: License :: OSI Approved :: BSD License
Classifier: Natural Language :: English
Classifier: Programming Language :: Python :: 3
Requires-Dist: click
Requires-Dist: paramiko
Requires-Dist: requests
